image_converter/__init__.py
image_converter/converter.py
image_converter_sarif-0.1.0.dist-info/licenses/LICENSE
image_converter_sarif-0.1.0.dist-info/METADATA
image_converter_sarif-0.1.0.dist-info/WHEEL
image_converter_sarif-0.1.0.dist-info/top_level.txt
image_converter_sarif-0.1.0.dist-info/RECORD
